consolor-0.1.2.dist-info/METADATA
consolor-0.1.2.dist-info/pydist.json
consolor-0.1.2.dist-info/DESCRIPTION.rst
consolor-0.1.2.dist-info/top_level.txt
consolor-0.1.2.dist-info/RECORD
consolor-0.1.2.dist-info/WHEEL
consolor/__init__.py
consolor/consolor.py
