Metadata-Version: 2.0
Name: consolor
Version: 0.1.2
Summary: Consolor provides highlighting functions for terminals.
Home-page: https://github.com/paetzke/consolor
Author: Friedrich Paetzke
Author-email: f.paetzke@gmail.com
License: BSD
Platform: UNKNOWN
Classifier: Environment :: Console
Classifier: Intended Audience :: Developers
Classifier: License :: OSI Approved :: BSD License
Classifier: Programming Language :: Python
Classifier: Programming Language :: Python :: 2
Classifier: Programming Language :: Python :: 2.7
Classifier: Programming Language :: Python :: 3
Classifier: Programming Language :: Python :: 3.3
Classifier: Programming Language :: Python :: Implementation :: CPython
Classifier: Programming Language :: Python :: Implementation :: PyPy
Classifier: Topic :: Software Development :: Libraries
Classifier: Topic :: Software Development :: User Interfaces
Classifier: Topic :: Terminals
Classifier: Topic :: Utilities
